prof/__init__.py
prof/main.so
prof/start.py
prof_tg_dooorto_qu-0.0.1.dist-info/METADATA
prof_tg_dooorto_qu-0.0.1.dist-info/WHEEL
prof_tg_dooorto_qu-0.0.1.dist-info/entry_points.txt
prof_tg_dooorto_qu-0.0.1.dist-info/top_level.txt
prof_tg_dooorto_qu-0.0.1.dist-info/RECORD
