Metadata-Version: 2.4
Name: prof-tg-dooorto-qu
Version: 0.0.1
Summary: نسخ صفقات من تيليجرام إلى منصة Quotex
Requires-Python: >=3.10
Requires-Dist: rich
Requires-Dist: telethon
Requires-Dist: pyfiglet
Requires-Dist: httpx
Requires-Dist: websocket-client
Requires-Dist: beautifulsoup4
Requires-Dist: pysocks
